nupgis/__init__.py
nupgis/ops.py
nupgis/struct.py
nupgis/validation.py
nupgis/simplification/__init__.py
nupgis/simplification/douglas_peucker.py
nupgis/simplification/lang.py
nupgis/simplification/reduction.py
nupgis/smoothing/__init__.py
nupgis/smoothing/sliding_average.py
nupgis-0.1.8.dist-info/licenses/LICENSE
nupgis-0.1.8.dist-info/METADATA
nupgis-0.1.8.dist-info/WHEEL
nupgis-0.1.8.dist-info/top_level.txt
nupgis-0.1.8.dist-info/RECORD
