Metadata-Version: 2.4
Name: nupgis
Version: 0.1.8
Summary: NUmPyGIS. A Python library for GIS using numpy only.
Author-email: Masum Billal <billalmasum93@gmail.com>
License:                                  Apache License
Requires-Python: >=3.11
License-File: LICENSE
Requires-Dist: numpy>=2.2.6
Dynamic: license-file
